cupychecker/__init__.py
cupychecker/checker.py
cupychecker/helpers.py
cupychecker/magic_runner.py
cupychecker/task_loader.py
cupychecker/exercises/modules/module_1/tasks/task_1.yaml
cupychecker-0.1.3.dist-info/METADATA
cupychecker-0.1.3.dist-info/WHEEL
cupychecker-0.1.3.dist-info/top_level.txt
cupychecker-0.1.3.dist-info/RECORD
